pdf_text_organizer/__init__.py
pdf_text_organizer/actions_manager.py
pdf_text_organizer/app.py
pdf_text_organizer/commands.py
pdf_text_organizer/events.py
pdf_text_organizer/exporters.py
pdf_text_organizer/extractor.py
pdf_text_organizer/models.py
pdf_text_organizer/validators.py
pdf_text_organizer/ui/__init__.py
pdf_text_organizer/ui/canvas_view.py
pdf_text_organizer/ui/dialogs.py
pdf_text_organizer/ui/page_view.py
pdf_text_organizer/ui/status_bar.py
pdf_text_organizer/ui/tree_view.py
pdf_text_organizer/utils/__init__.py
pdf_text_organizer/utils/config.py
pdf_text_organizer/utils/geometry.py
pdf_text_organizer-1.0.0.dist-info/METADATA
pdf_text_organizer-1.0.0.dist-info/WHEEL
pdf_text_organizer-1.0.0.dist-info/entry_points.txt
pdf_text_organizer-1.0.0.dist-info/top_level.txt
pdf_text_organizer-1.0.0.dist-info/RECORD
