Metadata-Version: 2.1
Name: pdf-text-organizer
Version: 1.0.0
Summary: PDF text extraction and spatial grouping tool - Vultus Serpentis demo application
Home-page: https://github.com/yourusername/pdf-text-organizer
Author: Vultus Serpentis Team
Project-URL: Documentation, https://github.com/yourusername/pdf-text-organizer/blob/main/README.md
Project-URL: Source, https://github.com/yourusername/pdf-text-organizer
Project-URL: Bug Tracker, https://github.com/yourusername/pdf-text-organizer/issues
Keywords: pdf text extraction grouping spatial-analysis gui tkinter
Classifier: Development Status :: 5 - Production/Stable
Classifier: Intended Audience :: End Users/Desktop
Classifier: Intended Audience :: Developers
Classifier: License :: OSI Approved :: MIT License
Classifier: Programming Language :: Python :: 3
Classifier: Programming Language :: Python :: 3.9
Classifier: Programming Language :: Python :: 3.10
Classifier: Programming Language :: Python :: 3.11
Classifier: Programming Language :: Python :: 3.12
Classifier: Topic :: Office/Business
Classifier: Topic :: Text Processing
Classifier: Topic :: Utilities
Requires-Python: >=3.9
Requires-Dist: vultus-serpentis (>=1.0.0)
Requires-Dist: pdfplumber (>=0.10.0)
Requires-Dist: ttkbootstrap (>=1.10.0)
